safebrowse/__init__.py
safebrowse/client.py
safebrowse/config.py
safebrowse/exceptions.py
safebrowse-0.3.2.dist-info/METADATA
safebrowse-0.3.2.dist-info/WHEEL
safebrowse-0.3.2.dist-info/top_level.txt
safebrowse-0.3.2.dist-info/RECORD
