Metadata-Version: 2.4
Name: safebrowse
Version: 0.3.2
Summary: Python SDK for SafeBrowse - AI-powered browser security with prompt injection detection
Home-page: https://github.com/aadil1/AI_Browser
Author: SafeBrowse
Author-email: aadilsayed19@gmail.com
Project-URL: Documentation, https://ai-browser-5d4p.onrender.com/docs
Project-URL: Source, https://github.com/aadil1/AI_Browser
Project-URL: Tracker, https://github.com/aadil1/AI_Browser/issues
Project-URL: Demo, https://ai-browser-5d4p.onrender.com
Keywords: ai security prompt-injection llm browser agent rag sanitization
Classifier: Development Status :: 4 - Beta
Classifier: Intended Audience :: Developers
Classifier: License :: OSI Approved :: MIT License
Classifier: Operating System :: OS Independent
Classifier: Programming Language :: Python :: 3
Classifier: Programming Language :: Python :: 3.10
Classifier: Programming Language :: Python :: 3.11
Classifier: Programming Language :: Python :: 3.12
Classifier: Programming Language :: Python :: 3.13
Classifier: Topic :: Security
Classifier: Topic :: Internet :: WWW/HTTP
Classifier: Topic :: Software Development :: Libraries :: Python Modules
Requires-Python: >=3.10
Requires-Dist: httpx>=0.24.0
Provides-Extra: dev
Requires-Dist: pytest>=7.0.0; extra == "dev"
Requires-Dist: pytest-asyncio>=0.20.0; extra == "dev"
Requires-Dist: pytest-cov>=4.0.0; extra == "dev"
Dynamic: author
Dynamic: author-email
Dynamic: classifier
Dynamic: description
Dynamic: description-content-type
Dynamic: home-page
Dynamic: keywords
Dynamic: project-url
Dynamic: provides-extra
Dynamic: requires-dist
Dynamic: requires-python
Dynamic: summary
